django_quick_auth/__init__.py
django_quick_auth/apps.py
django_quick_auth/authentication.py
django_quick_auth/models.py
django_quick_auth/serializers.py
django_quick_auth/settings.py
django_quick_auth/urls.py
django_quick_auth/views.py
django_quick_auth/migrations/0001_initial.py
django_quick_auth/migrations/__init__.py
django_quick_auth/tests/__init__.py
django_quick_auth/tests/test_models.py
django_quick_auth/tests/test_serailizers.py
django_quick_auth/tests/test_settings.py
django_quick_auth/tests/test_views.py
django_quick_auth/tests/urls.py
tc_django_quick_auth-0.1.2.dist-info/LICENSE
tc_django_quick_auth-0.1.2.dist-info/METADATA
tc_django_quick_auth-0.1.2.dist-info/WHEEL
tc_django_quick_auth-0.1.2.dist-info/top_level.txt
tc_django_quick_auth-0.1.2.dist-info/RECORD
