Metadata-Version: 2.1
Name: tc-django-quick-auth
Version: 0.1.2
Summary: A reusable Django package for quick login and signup endpoints with optional JWT authentication
Home-page: https://github.com/Darkbeast-glitch/django-quick-auth
Author: Julius Boakye
Author-email: juliusboakye@pythonghana.org
License: UNKNOWN
Keywords: django,authentication,jwt,login,signup,api
Platform: UNKNOWN
Classifier: Programming Language :: Python :: 3
Classifier: Programming Language :: Python :: 3.6
Classifier: Programming Language :: Python :: 3.7
Classifier: Programming Language :: Python :: 3.8
Classifier: Programming Language :: Python :: 3.9
Classifier: Programming Language :: Python :: 3.10
Classifier: License :: OSI Approved :: MIT License
Classifier: Operating System :: OS Independent
Classifier: Framework :: Django
Classifier: Framework :: Django :: 3.2
Classifier: Intended Audience :: Developers
Classifier: Topic :: Software Development :: Libraries :: Python Modules
Requires-Python: >=3.6
License-File: LICENSE
Requires-Dist: django>=3.2
Requires-Dist: djangorestframework>=3.12
Requires-Dist: djangorestframework-simplejwt>=5.2
